phenopacket_store_toolkit-0.1.6.dist-info/licenses/LICENSE
ppktstore/__init__.py
ppktstore/__main__.py
ppktstore/_zip_util.py
ppktstore/model.py
ppktstore/py.typed
ppktstore/registry/__init__.py
ppktstore/registry/_api.py
ppktstore/registry/_config.py
ppktstore/registry/_github.py
ppktstore/release/__init__.py
ppktstore/release/archive/__init__.py
ppktstore/release/archive/_archiver.py
ppktstore/release/archive/_impl.py
ppktstore/release/report/__init__.py
ppktstore/release/report/_report.py
ppktstore/release/stats/__init__.py
ppktstore/release/stats/_ppkt_store_stats.py
ppktstore/release/stats/_summary.py
ppktstore/release/stats/_test_summary.py
ppktstore/validation/__init__.py
ppktstore/validation/_impl.py
ppktstore/validation/_ps_auditor.py
phenopacket_store_toolkit-0.1.6.dist-info/METADATA
phenopacket_store_toolkit-0.1.6.dist-info/WHEEL
phenopacket_store_toolkit-0.1.6.dist-info/top_level.txt
phenopacket_store_toolkit-0.1.6.dist-info/RECORD
