Metadata-Version: 2.4
Name: phenopacket-store-toolkit
Version: 0.1.6
Summary: Collection of GA4GH Phenopackets
Author-email: Daniel Danis <daniel.danis@bih-charite.de>, Peter Robinson <peter.robinson@bih-charite.de>
License: BSD 3-Clause License
Project-URL: homepage, https://github.com/monarch-initiative/phenopacket-store-toolkit
Project-URL: repository, https://github.com/monarch-initiative/phenopacket-store-toolkit.git
Project-URL: documentation, https://github.com/monarch-initiative/phenopacket-store-toolkit
Project-URL: bugtracker, https://github.com/monarch-initiative/phenopacket-store-toolkit/issues
Keywords: Global Alliance for Genomics and Health,GA4GH Phenopacket Schema,Human Phenotype Ontology,GA4GH,HPO
Classifier: Development Status :: 3 - Alpha
Classifier: License :: OSI Approved :: MIT License
Classifier: Operating System :: OS Independent
Classifier: Programming Language :: Python :: 3.10
Classifier: Programming Language :: Python :: 3.11
Classifier: Programming Language :: Python :: 3.12
Requires-Python: >=3.10
License-File: LICENSE
Requires-Dist: phenopackets>=2.0.2.post4
Requires-Dist: certifi
Provides-Extra: release
Requires-Dist: mdutils>=1.6.0; extra == "release"
Requires-Dist: stairval>=0.2.0; extra == "release"
Requires-Dist: matplotlib<4.0.0,>=3.7.2; extra == "release"
Requires-Dist: numpy<2.0.0,>=1.24.2; extra == "release"
Requires-Dist: pandas<3.0.0,>=2.0.0; extra == "release"
Requires-Dist: seaborn<1.0.0,>=0.12.2; extra == "release"
Requires-Dist: phenosentry>=0.3.1; extra == "release"
Provides-Extra: test
Requires-Dist: pytest<8.0.0,>=7.0.0; extra == "test"
Requires-Dist: tox<5.0.0,>=4.0.0; extra == "test"
Requires-Dist: ruff>=0.12.0; extra == "test"
Provides-Extra: docs
Requires-Dist: sphinx>=7.0.0; extra == "docs"
Requires-Dist: sphinx-rtd-theme>=1.3.0; extra == "docs"
Requires-Dist: sphinx-copybutton>=0.5.0; extra == "docs"
Dynamic: license-file
